heidpi/__init__.py
heidpi/heiDPI_env.py
heidpi/heiDPI_logger.py
heidpi/heiDPIsrvd.py
heidpi/version.py
heidpi/schema/README.md
heidpi/schema/daemon_event_schema.json
heidpi/schema/error_event_schema.json
heidpi/schema/flow_event_schema.json
heidpi/schema/packet_event_schema.json
heidpi-1.3.0.dist-info/METADATA
heidpi-1.3.0.dist-info/WHEEL
heidpi-1.3.0.dist-info/entry_points.txt
heidpi-1.3.0.dist-info/licenses/LICENSE
heidpi-1.3.0.dist-info/RECORD
