Metadata-Version: 2.1
Name: heiDPI
Version: 1.3.0
Summary: nDPId consumer implementation
Project-URL: Homepage, https://github.com/stefanDeveloper/heiDPI
Project-URL: Bug Tracker, https://github.com/stefanDeveloper/heiDPI/issues
Author-email: Stefan Machmeier <stefan.machmeier@uni-heidelberg.de>
License:                     GNU GENERAL PUBLIC LICENSE
License-File: LICENSE
Classifier: Intended Audience :: Developers
Classifier: Intended Audience :: Information Technology
Classifier: Intended Audience :: Science/Research
Classifier: Intended Audience :: System Administrators
Classifier: Intended Audience :: Telecommunications Industry
Classifier: License :: OSI Approved :: European Union Public Licence 1.2 (EUPL 1.2)
Classifier: Operating System :: OS Independent
Classifier: Programming Language :: Python :: 3
Classifier: Programming Language :: Python :: 3 :: Only
Classifier: Programming Language :: Python :: 3.7
Classifier: Programming Language :: Python :: 3.8
Classifier: Programming Language :: Python :: 3.9
Classifier: Programming Language :: Python :: 3.10
Classifier: Programming Language :: Python :: 3.11
Classifier: Topic :: Internet :: Log Analysis
Classifier: Topic :: Security
Classifier: Topic :: System :: Networking :: Monitoring
Requires-Python: >=3.6
